{
  "project_info": {
    "project_number": "672012855885",
    "project_id": "fir-authentication-6dd3f",
    "storage_bucket": "fir-authentication-6dd3f.appspot.com"
  },
  "client": [
    {
      "client_info": {
        "mobilesdk_app_id": "1:672012855885:android:fd88d06b93395f3604ca04",
        "android_client_info": {
          "package_name": "com.korkmazanil.firebaseauthentication"
        }
      },
      "oauth_client": [
        {
          "client_id": "672012855885-jl2ogu4gi23lji2v22ghk42c6a1bc85o.apps.googleusercontent.com",
          "client_type": 3
        }
      ],
      "api_key": [
        {
          "current_key": "AIzaSyAEh4sZM0fyXjVoCkfZ124r5sDfPIjVLII"
        }
      ],
      "services": {
        "appinvite_service": {
          "other_platform_oauth_client": [
            {
              "client_id": "672012855885-jl2ogu4gi23lji2v22ghk42c6a1bc85o.apps.googleusercontent.com",
              "client_type": 3
            }
          ]
        }
      }
    }
  ],
  "configuration_version": "1"
}